edge_sam/__init__.py
edge_sam/automatic_mask_generator.py
edge_sam/build_sam.py
edge_sam/config.py
edge_sam/predictor.py
edge_sam/modeling/__init__.py
edge_sam/modeling/common.py
edge_sam/modeling/image_encoder.py
edge_sam/modeling/mask_decoder.py
edge_sam/modeling/prompt_encoder.py
edge_sam/modeling/rep_vit.py
edge_sam/modeling/sam.py
edge_sam/modeling/sam_batch.py
edge_sam/modeling/transformer.py
edge_sam/modeling/projects/__init__.py
edge_sam/modeling/projects/EfficientDet/__init__.py
edge_sam/modeling/projects/EfficientDet/convert_tf_to_pt.py
edge_sam/modeling/projects/EfficientDet/efficientdet/__init__.py
edge_sam/modeling/projects/EfficientDet/efficientdet/bifpn.py
edge_sam/modeling/projects/EfficientDet/efficientdet/efficientdet.py
edge_sam/modeling/projects/EfficientDet/efficientdet/efficientdet_head.py
edge_sam/modeling/projects/EfficientDet/efficientdet/huber_loss.py
edge_sam/modeling/projects/EfficientDet/efficientdet/utils.py
edge_sam/modeling/projects/EfficientDet/efficientdet/tensorflow/__init__.py
edge_sam/modeling/projects/EfficientDet/efficientdet/tensorflow/anchor_generator.py
edge_sam/modeling/projects/EfficientDet/efficientdet/tensorflow/coco_90class.py
edge_sam/modeling/projects/EfficientDet/efficientdet/tensorflow/coco_90metric.py
edge_sam/modeling/projects/EfficientDet/efficientdet/tensorflow/trans_max_iou_assigner.py
edge_sam/modeling/projects/EfficientDet/efficientdet/tensorflow/yxyx_bbox_coder.py
edge_sam/modeling/projects/EfficientDet/efficientdet/tensorflow/api_wrappers/__init__.py
edge_sam/modeling/projects/EfficientDet/efficientdet/tensorflow/api_wrappers/coco_api.py
edge_sam/onnx/__init__.py
edge_sam/onnx/predictor_onnx.py
edge_sam/utils/__init__.py
edge_sam/utils/amg.py
edge_sam/utils/common.py
edge_sam/utils/coreml.py
edge_sam/utils/transforms.py
visaionedgesam-1.0.dist-info/licenses/LICENSE
visaionedgesam-1.0.dist-info/METADATA
visaionedgesam-1.0.dist-info/WHEEL
visaionedgesam-1.0.dist-info/top_level.txt
visaionedgesam-1.0.dist-info/RECORD
